plower/__init__.py
plower/common.py
plower/imports.py
plower/wave_spectrum.py
plower-0.0.9b0.dist-info/LICENSE.txt
plower-0.0.9b0.dist-info/METADATA
plower-0.0.9b0.dist-info/WHEEL
plower-0.0.9b0.dist-info/top_level.txt
plower-0.0.9b0.dist-info/RECORD
