Metadata-Version: 2.1
Name: plower
Version: 0.0.9b0
Summary: Processing Library for Ocean Wave and Energy Resource Data (PLOWER): A python library that process the wave data provided by National Buoy Data Center and outputs histograms and other statistics
Home-page: https://github.com/ckesanapalli/plower/
Author: Chaitanya Kesanapalli
Author-email: ckesanapalli@gmail.com
License: BSD 3-Clause License
Project-URL: Documentation, https://github.com/ckesanapalli/plower/README.rst
Platform: any
Classifier: Development Status :: 1 - Planning
Classifier: Programming Language :: Python :: 3
Classifier: Programming Language :: Python :: 3.8
Classifier: Programming Language :: Python :: 3.9
Classifier: Programming Language :: Python :: 3.10
Classifier: License :: OSI Approved :: BSD License
Classifier: Operating System :: OS Independent
Classifier: Intended Audience :: Science/Research
Classifier: Topic :: Scientific/Engineering :: Physics
License-File: LICENSE.txt
Requires-Dist: numpy
Requires-Dist: pandas
Requires-Dist: scipy
Requires-Dist: xarray
Requires-Dist: dask
Requires-Dist: joblib
Requires-Dist: pyscaffold
Requires-Dist: black
Requires-Dist: coverage
Requires-Dist: hypothesis
Requires-Dist: pytest
Requires-Dist: pytest-cov
Requires-Dist: setuptools
Requires-Dist: sphinx
Requires-Dist: sphinx-copybutton
Requires-Dist: sphinx-rtd-theme
Requires-Dist: sphinx-automodapi
Requires-Dist: furo
Requires-Dist: tox
Requires-Dist: tox-conda
Requires-Dist: pre-commit
Requires-Dist: lxml
Requires-Dist: beautifulsoup4
Requires-Dist: html5lib
Requires-Dist: sphinxemoji
Requires-Dist: loguru
Requires-Dist: requests
Requires-Dist: importlib-metadata ; python_version < "3.8"
Provides-Extra: testing
Requires-Dist: setuptools ; extra == 'testing'
Requires-Dist: pytest ; extra == 'testing'
Requires-Dist: pytest-cov ; extra == 'testing'
